neocogs/__init__.py
neocogs/core.py
neocogs/fs.py
neocogs/log.py
neocogs/run.py
neocogs/std.py
NeoCogs-0.4.5a1.dist-info/LICENSE
NeoCogs-0.4.5a1.dist-info/METADATA
NeoCogs-0.4.5a1.dist-info/WHEEL
NeoCogs-0.4.5a1.dist-info/entry_points.txt
NeoCogs-0.4.5a1.dist-info/top_level.txt
NeoCogs-0.4.5a1.dist-info/RECORD
