Metadata-Version: 2.1
Name: NeoCogs
Version: 0.4.5a1
Summary: Toolkit for developing command-line utilities in Python
Home-page: https://github.com/Krono159/NeoCogs
Download-URL: http://pypi.python.org/pypi/NeoCogs
Author: Kirill Simonov (Prometheus Research, LLC), Rework by Luis S. (MoccaDev)
Author-email: krono159@proton.me
License: MIT
Classifier: Development Status :: 2 - Pre-Alpha
Classifier: Environment :: Console
Classifier: Intended Audience :: Developers
Classifier: Intended Audience :: System Administrators
Classifier: License :: OSI Approved :: MIT License
Classifier: Operating System :: POSIX :: Linux
Classifier: Programming Language :: Python
Classifier: Programming Language :: Python :: 3
Classifier: Topic :: Utilities
License-File: LICENSE
Requires-Dist: setuptools
Requires-Dist: PyYAML
